pallas/__init__.py
pallas/_compat.py
pallas/assembly.py
pallas/caching.py
pallas/client.py
pallas/conversions.py
pallas/csv.py
pallas/exceptions.py
pallas/info.py
pallas/proxies.py
pallas/py.typed
pallas/results.py
pallas/sql.py
pallas/testing.py
pallas/utils.py
pallas/storage/__init__.py
pallas/storage/base.py
pallas/storage/filesystem.py
pallas/storage/memory.py
pallas/storage/s3.py
pallas-0.10.dist-info/LICENSE
pallas-0.10.dist-info/METADATA
pallas-0.10.dist-info/NOTICE
pallas-0.10.dist-info/WHEEL
pallas-0.10.dist-info/top_level.txt
pallas-0.10.dist-info/RECORD
