Metadata-Version: 2.1
Name: pallas
Version: 0.10
Summary: AWS Athena client
Home-page: https://github.com/akamai/pallas
Author: Miloslav Pojman
Author-email: mpojman@akamai.com
License: Apache License 2.0
Project-URL: Documentation, https://pallas.readthedocs.io/
Project-URL: Source Code, https://github.com/akamai/pallas
Keywords: Amazon,Athena,AWS,database,db,Jupyter,Presto,SQL
Platform: UNKNOWN
Classifier: Framework :: IPython
Classifier: Framework :: Jupyter
Classifier: Intended Audience :: Science/Research
Classifier: Intended Audience :: Developers
Classifier: License :: OSI Approved :: Apache Software License
Classifier: Operating System :: OS Independent
Classifier: Programming Language :: Python
Classifier: Programming Language :: Python :: 3
Classifier: Programming Language :: Python :: 3.7
Classifier: Programming Language :: Python :: 3.8
Classifier: Programming Language :: Python :: Implementation :: CPython
Classifier: Programming Language :: SQL
Classifier: Topic :: Database
Classifier: Topic :: Scientific/Engineering
Classifier: Topic :: Software Development :: Libraries
Classifier: Topic :: Software Development :: Libraries :: Python Modules
Classifier: Typing :: Typed
Requires-Python: >=3.7
License-File: LICENSE
License-File: NOTICE
Requires-Dist: boto3
Provides-Extra: dev
Requires-Dist: flake8 ; extra == 'dev'
Requires-Dist: pytest ; extra == 'dev'
Requires-Dist: mypy ; extra == 'dev'
Provides-Extra: pandas
Requires-Dist: pandas (>=1.0.0) ; extra == 'pandas'
